{
  "version": "1.0",
  "timestamp": "2025-03-22T19:03:09.459Z",
  "feeds": [
    {
      "type": "rss",
      "url": "http://juridikpodden.libsyn.com/rss",
      "maxEpisodes": 3,
      "playedEpisodes": [],
      "playbackPositions": {}
    },
    {
      "type": "rss",
      "url": "https://www.patreon.com/rss/kungarochkrig?auth=xwWZm_wjlaOXcfWz2Ew5suk3gBs-TNAy&show=874057",
      "maxEpisodes": 3,
      "playedEpisodes": [],
      "playbackPositions": {}
    },
    {
      "type": "live",
      "name": "Sveriges Radio P1",
      "url": "https://sverigesradio.se/topsy/direkt/132-hi-mp3",
      "description": "Sveriges Radio P1 - News and culture from Swedish Radio"
    },
    {
      "type": "live",
      "name": "Sverige Raddio P3",
      "url": "https://sverigesradio.se/topsy/direkt/164-hi.mp3",
      "description": "Contemporary music and entertainment"
    }
  ]
}